that_depends/__init__.py
that_depends/container.py
that_depends/entities/__init__.py
that_depends/entities/resource_context.py
that_depends/exceptions.py
that_depends/experimental/__init__.py
that_depends/experimental/providers.py
that_depends/injection.py
that_depends/integrations/__init__.py
that_depends/integrations/fastapi.py
that_depends/integrations/faststream.py
that_depends/meta.py
that_depends/providers/__init__.py
that_depends/providers/base.py
that_depends/providers/collection.py
that_depends/providers/context_resources.py
that_depends/providers/factories.py
that_depends/providers/local_singleton.py
that_depends/providers/mixin.py
that_depends/providers/object.py
that_depends/providers/resources.py
that_depends/providers/selector.py
that_depends/providers/singleton.py
that_depends/providers/state.py
that_depends/py.typed
that_depends/utils.py
that_depends-3.9.0.dist-info/WHEEL
that_depends-3.9.0.dist-info/METADATA
that_depends-3.9.0.dist-info/RECORD
