Metadata-Version: 2.4
Name: that-depends
Version: 3.9.0
Summary: Simple Dependency Injection framework
Keywords: di,dependency injector,ioc-container,mocks,python
Author: Artur Shiriev
Author-email: Artur Shiriev <me@shiriev.ru>
License-Expression: MIT
Classifier: Programming Language :: Python :: 3.10
Classifier: Programming Language :: Python :: 3.11
Classifier: Programming Language :: Python :: 3.12
Classifier: Programming Language :: Python :: 3.13
Classifier: Programming Language :: Python :: 3.14
Classifier: Typing :: Typed
Classifier: Topic :: Software Development :: Libraries
Requires-Dist: fastapi ; extra == 'fastapi'
Requires-Dist: faststream ; extra == 'faststream'
Requires-Python: >=3.10, <4
Project-URL: docs, https://that-depends.readthedocs.io
Project-URL: repository, https://github.com/modern-python/that-depends
Provides-Extra: fastapi
Provides-Extra: faststream
